Workbook

Sheet Assumptions
A1: Pedalshield — Model Assumptions (blue = change me)
A3: ZEC price ($) | B3: 426 | C3: Source: CoinGecko via Cointelegraph, 6/8/2026 — VOLATILE
A4: Avg km per ride | B4: 9
A5: Rides per rider per month | B5: 10
A6: Starting riders (month 1, from waitlist) | B6: 1000
A7: Rider growth %/mo — Phase 1 (m1-6) | B7: 0.2
A8: Rider growth %/mo — Phase 2 (m7-18) | B8: 0.15
A9: Rider growth %/mo — Phase 3 (m19-36) | B9: 0.1
A11: Emission tier 1 ZEC/km | B11: 0.0002 | C11: Current PEDALSHIELD_ZAT_PER_KM=20000
A12: Tier 1 applies below riders | B12: 5000
A13: Emission tier 2 ZEC/km | B13: 5e-05 | C13: SCALE_PLAN taper
A14: Tier 2 applies below riders | B14: 50000
A15: Emission tier 3 ZEC/km | B15: 2e-05
A17: Premium conversion | B17: 0.05
A18: Premium price $/mo | B18: 5.99
A19: Affiliate margin $/rider/mo | B19: 0.1
A20: Sponsor pools start month | B20: 10
A21: Sponsor base $/mo | B21: 5000
A22: Sponsor growth %/mo | B22: 0.1
A23: Corporate wellness start month | B23: 20
A24: Wellness base $/mo | B24: 8000
A25: Wellness growth %/mo | B25: 0.12
A27: FTEs Phase 1 | B27: 3
... A32: Infra $/rider/mo | B32: 0.05
A33: CAC $/new rider | B33: 4 | C33: Privacy-community organic heavy
A34: Other/compliance base $/mo | B34: 2000
A35: Other % of revenue | B35: 0.05
A37: Seed raised ($) | B37: 2000000
A39: Founder ownership at exit | B39: 0.55 | C39: Post seed + Series A + option pool

Sheet Model
A1: Pedalshield — 36-Month Operating Model ($)
A2: Month | B2: 1 | C2: 2 | D2: 3 | E2: 4 | F2: 5 | G2: 6 | H2: 7 | I2: 8 | J2: 9 | K2: 10 | L2: 11 | M2: 12 | N2: 13 | O2: 14 | P2: 15 | Q2: 16 | R2: 17 | S2: 18 | T2: 19 | U2: 20 | V2: 21 | W2: 22 | X2: 23 | Y2: 24 | Z2: 25 | AA2: 26 | AB2: 27 | AC2: 28 | AD2: 29 | AE2: 30 | AF2: 31 | AG2: 32 | AH2: 33 | AI2: 34 | AJ2: 35 | AK2: 36
A3: Phase | B3: =IF(B2<=6,1,IF(B2<=18,2,3)) -> 1 | C3: =IF(C2<=6,1,IF(C2<=18,2,3)) -> 1 | D3: =IF(D2<=6,1,IF(D2<=18,2,3)) -> 1 | E3: =IF(E2<=6,1,IF(E2<=18,2,3)) -> 1 | F3: =IF(F2<=6,1,IF(F2<=18,2,3)) -> 1 | G3: =IF(G2<=6,1,IF(G2<=18,2,3)) -> 1 | H3: =IF(H2<=6,1,IF(H2<=18,2,3)) -> 2 | I3: =IF(I2<=6,1,IF(I2<=18,2,3)) -> 2 | ... AK3: =IF(AK2<=6,1,IF(AK2<=18,2,3)) -> 3
A4: Rider growth % | B4: =CHOOSE(B3,Assumptions!$B$7,Assumptions!$B$8,Assumptions!$B$9) -> 0.2 | C4: =CHOOSE(C3,Assumptions!$B$7,Assumptions!$B$8,Assumptions!$B$9) -> 0.2 | D4: =CHOOSE(D3,Assumptions!$B$7,Assumptions!$B$8,Assumptions!$B$9) -> 0.2 | E4: =CHOOSE(E3,Assumptions!$B$7,Assumptions!$B$8,Assumptions!$B$9) -> 0.2 | F4: =CHOOSE(F3,Assumptions!$B$7,Assumptions!$B$8,Assumptions!$B$9) -> 0.2 | G4: =CHOOSE(G3,Assumptions!$B$7,Assumptions!$B$8,Assumptions!$B$9) -> 0.2 | H4: =CHOOSE(H3,Assumptions!$B$7,Assumptions!$B$8,Assumptions!$B$9) -> 0.15 | I4: =CHOOSE(I3,Assumptions!$B$7,Assumptions!$B$8,Assumptions!$B$9) -> 0.15 | ... AK4: =CHOOSE(AK3,Assumptions!$B$7,Assumptions!$B$8,Assumptions!$B$9) -> 0.1
A5: Active riders | B5: =Assumptions!$B$6 -> 1000 | C5: =ROUND(B5*(1+C4),0) -> 1200 | D5: =ROUND(C5*(1+D4),0) -> 1440 | E5: =ROUND(D5*(1+E4),0) -> 1728 | F5: =ROUND(E5*(1+F4),0) -> 2074 | G5: =ROUND(F5*(1+G4),0) -> 2489 | H5: =ROUND(G5*(1+H4),0) -> 2862 | I5: =ROUND(H5*(1+I4),0) -> 3291 | J5: =ROUND(I5*(1+J4),0) -> 3785 | ... AK5: =ROUND(AJ5*(1+AK4),0) -> 74039
A6: New riders | B6: =B5 -> 1000 | C6: =C5-B5 -> 200 | D6: =D5-C5 -> 240 | E6: =E5-D5 -> 288 | F6: =F5-E5 -> 346 | G6: =G5-F5 -> 415 | H6: =H5-G5 -> 373 | I6: =I5-H5 -> 429 | J6: =J5-I5 -> 494 | ... AK6: =AK5-AJ5 -> 6731
A7: Rides /mo | B7: =B5*Assumptions!$B$5 -> 10000 | C7: =C5*Assumptions!$B$5 -> 12000 | D7: =D5*Assumptions!$B$5 -> 14400 | E7: =E5*Assumptions!$B$5 -> 17280 | F7: =F5*Assumptions!$B$5 -> 20740 | G7: =G5*Assumptions!$B$5 -> 24890 | H7: =H5*Assumptions!$B$5 -> 28620 | I7: =I5*Assumptions!$B$5 -> 32910 | ... AK7: =AK5*Assumptions!$B$5 -> 740390
A8: Verified km /mo | B8: =B7*Assumptions!$B$4 -> 90000 | C8: =C7*Assumptions!$B$4 -> 108000 | D8: =D7*Assumptions!$B$4 -> 129600 | E8: =E7*Assumptions!$B$4 -> 155520 | F8: =F7*Assumptions!$B$4 -> 186660 | G8: =G7*Assumptions!$B$4 -> 224010 | H8: =H7*Assumptions!$B$4 -> 257580 | I8: =I7*Assumptions!$B$4 -> 296190 | ... AK8: =AK7*Assumptions!$B$4 -> 6663510
A9: Emission (ZEC/km) | B9: =IF(B5<Assumptions!$B$12,Assumptions!$B$11,IF(B5<Assumptions!$B$14,Assumptions!$B$13,Assumptions!$B$15)) -> 0.0002 | C9: =IF(C5<Assumptions!$B$12,Assumptions!$B$11,IF(C5<Assumptions!$B$14,Assumptions!$B$13,Assumptions!$B$15)) -> 0.0002 | D9: =IF(D5<Assumptions!$B$12,Assumptions!$B$11,IF(D5<Assumptions!$B$14,Assumptions!$B$13,Assumptions!$B$15)) -> 0.0002 | E9: =IF(E5<Assumptions!$B$12,Assumptions!$B$11,IF(E5<Assumptions!$B$14,Assumptions!$B$13,Assumptions!$B$15)) -> 0.0002 | F9: =IF(F5<Assumptions!$B$12,Assumptions!$B$11,IF(F5<Assumptions!$B$14,Assumptions!$B$13,Assumptions!$B$15)) -> 0.0002 | G9: =IF(G5<Assumptions!$B$12,Assumptions!$B$11,IF(G5<Assumptions!$B$14,Assumptions!$B$13,Assumptions!$B$15)) -> 0.0002 | H9: =IF(H5<Assumptions!$B$12,Assumptions!$B$11,IF(H5<Assumptions!$B$14,Assumptions!$B$13,Assumptions!$B$15)) -> 0.0002 | I9: =IF(I5<Assumptions!$B$12,Assumptions!$B$11,IF(I5<Assumptions!$B$14,Assumptions!$B$13,Assumptions!$B$15)) -> 0.0002 | ... AK9: =IF(AK5<Assumptions!$B$12,Assumptions!$B$11,IF(AK5<Assumptions!$B$14,Assumptions!$B$13,Assumptions!$B$15)) -> 2e-05
A10: Reward burn (ZEC) | B10: =B8*B9 -> 18 | C10: =C8*C9 -> 21.6 | D10: =D8*D9 -> 25.92 | E10: =E8*E9 -> 31.104 | F10: =F8*F9 -> 37.332 | G10: =G8*G9 -> 44.802 | H10: =H8*H9 -> 51.516 | I10: =I8*I9 -> 59.238 | ... AK10: =AK8*AK9 -> 133.2702
A11: Reward burn ($) | B11: =B10*Assumptions!$B$3 -> 7668 | C11: =C10*Assumptions!$B$3 -> 9201.6 | D11: =D10*Assumptions!$B$3 -> 11041.92 | E11: =E10*Assumptions!$B$3 -> 13250.304 | F11: =F10*Assumptions!$B$3 -> 15903.432 | G11: =G10*Assumptions!$B$3 -> 19085.652 | H11: =H10*Assumptions!$B$3 -> 21945.816 | I11: =I10*Assumptions!$B$3 -> 25235.388 | ... AK11: =AK10*Assumptions!$B$3 -> 56773.105
A13: Premium subscriptions | B13: =B5*Assumptions!$B$17*Assumptions!$B$18 -> 299.5 | C13: =C5*Assumptions!$B$17*Assumptions!$B$18 -> 359.4 | D13: =D5*Assumptions!$B$17*Assumptions!$B$18 -> 431.28 | E13: =E5*Assumptions!$B$17*Assumptions!$B$18 -> 517.536 | F13: =F5*Assumptions!$B$17*Assumptions!$B$18 -> 621.163 | G13: =G5*Assumptions!$B$17*Assumptions!$B$18 -> 745.4555 | H13: =H5*Assumptions!$B$17*Assumptions!$B$18 -> 857.169 | I13: =I5*Assumptions!$B$17*Assumptions!$B$18 -> 985.6545 | ... AK13: =AK5*Assumptions!$B$17*Assumptions!$B$18 -> 22174.68
A14: Affiliate/gear margin | B14: =B5*Assumptions!$B$19 -> 100 | C14: =C5*Assumptions!$B$19 -> 120 | D14: =D5*Assumptions!$B$19 -> 144 | E14: =E5*Assumptions!$B$19 -> 172.8 | F14: =F5*Assumptions!$B$19 -> 207.4 | G14: =G5*Assumptions!$B$19 -> 248.9 | H14: =H5*Assumptions!$B$19 -> 286.2 | I14: =I5*Assumptions!$B$19 -> 329.1 | ... AK14: =AK5*Assumptions!$B$19 -> 7403.9
A15: Sponsor pools | B15: =IF(B2>=Assumptions!$B$20,Assumptions!$B$21*(1+Assumptions!$B$22)^(B2-Assumptions!$B$20),0) -> 0 | C15: =IF(C2>=Assumptions!$B$20,Assumptions!$B$21*(1+Assumptions!$B$22)^(C2-Assumptions!$B$20),0) -> 0 | D15: =IF(D2>=Assumptions!$B$20,Assumptions!$B$21*(1+Assumptions!$B$22)^(D2-Assumptions!$B$20),0) -> 0 | E15: =IF(E2>=Assumptions!$B$20,Assumptions!$B$21*(1+Assumptions!$B$22)^(E2-Assumptions!$B$20),0) -> 0 | F15: =IF(F2>=Assumptions!$B$20,Assumptions!$B$21*(1+Assumptions!$B$22)^(F2-Assumptions!$B$20),0) -> 0 | G15: =IF(G2>=Assumptions!$B$20,Assumptions!$B$21*(1+Assumptions!$B$22)^(G2-Assumptions!$B$20),0) -> 0 | H15: =IF(H2>=Assumptions!$B$20,Assumptions!$B$21*(1+Assumptions!$B$22)^(H2-Assumptions!$B$20),0) -> 0 | I15: =IF(I2>=Assumptions!$B$20,Assumptions!$B$21*(1+Assumptions!$B$22)^(I2-Assumptions!$B$20),0) -> 0 | ... AK15: =IF(AK2>=Assumptions!$B$20,Assumptions!$B$21*(1+Assumptions!$B$22)^(AK2-Assumptions!$B$20),0) -> 59590.883
A16: Corporate wellness | B16: =IF(B2>=Assumptions!$B$23,Assumptions!$B$24*(1+Assumptions!$B$25)^(B2-Assumptions!$B$23),0) -> 0 | C16: =IF(C2>=Assumptions!$B$23,Assumptions!$B$24*(1+Assumptions!$B$25)^(C2-Assumptions!$B$23),0) -> 0 | D16: =IF(D2>=Assumptions!$B$23,Assumptions!$B$24*(1+Assumptions!$B$25)^(D2-Assumptions!$B$23),0) -> 0 | E16: =IF(E2>=Assumptions!$B$23,Assumptions!$B$24*(1+Assumptions!$B$25)^(E2-Assumptions!$B$23),0) -> 0 | F16: =IF(F2>=Assumptions!$B$23,Assumptions!$B$24*(1+Assumptions!$B$25)^(F2-Assumptions!$B$23),0) -> 0 | G16: =IF(G2>=Assumptions!$B$23,Assumptions!$B$24*(1+Assumptions!$B$25)^(G2-Assumptions!$B$23),0) -> 0 | H16: =IF(H2>=Assumptions!$B$23,Assumptions!$B$24*(1+Assumptions!$B$25)^(H2-Assumptions!$B$23),0) -> 0 | I16: =IF(I2>=Assumptions!$B$23,Assumptions!$B$24*(1+Assumptions!$B$25)^(I2-Assumptions!$B$23),0) -> 0 | ... AK16: =IF(AK2>=Assumptions!$B$23,Assumptions!$B$24*(1+Assumptions!$B$25)^(AK2-Assumptions!$B$23),0) -> 49043.149
A17: Total revenue | B17: =SUM(B13:B16) -> 399.5 | C17: =SUM(C13:C16) -> 479.4 | D17: =SUM(D13:D16) -> 575.28 | E17: =SUM(E13:E16) -> 690.336 | F17: =SUM(F13:F16) -> 828.563 | G17: =SUM(G13:G16) -> 994.3555 | H17: =SUM(H13:H16) -> 1143.369 | I17: =SUM(I13:I16) -> 1314.7545 | ... AK17: =SUM(AK13:AK16) -> 138212.61
A19: Team | B19: =CHOOSE(B3,Assumptions!$B$27,Assumptions!$B$28,Assumptions!$B$29)*Assumptions!$B$30/12 -> 45000 | C19: =CHOOSE(C3,Assumptions!$B$27,Assumptions!$B$28,Assumptions!$B$29)*Assumptions!$B$30/12 -> 45000 | D19: =CHOOSE(D3,Assumptions!$B$27,Assumptions!$B$28,Assumptions!$B$29)*Assumptions!$B$30/12 -> 45000 | E19: =CHOOSE(E3,Assumptions!$B$27,Assumptions!$B$28,Assumptions!$B$29)*Assumptions!$B$30/12 -> 45000 | F19: =CHOOSE(F3,Assumptions!$B$27,Assumptions!$B$28,Assumptions!$B$29)*Assumptions!$B$30/12 -> 45000 | G19: =CHOOSE(G3,Assumptions!$B$27,Assumptions!$B$28,Assumptions!$B$29)*Assumptions!$B$30/12 -> 45000 | H19: =CHOOSE(H3,Assumptions!$B$27,Assumptions!$B$28,Assumptions!$B$29)*Assumptions!$B$30/12 -> 75000 | I19: =CHOOSE(I3,Assumptions!$B$27,Assumptions!$B$28,Assumptions!$B$29)*Assumptions!$B$30/12 -> 75000 | ... AK19: =CHOOSE(AK3,Assumptions!$B$27,Assumptions!$B$28,Assumptions!$B$29)*Assumptions!$B$30/12 -> 135000
A20: Infra | B20: =Assumptions!$B$31+B5*Assumptions!$B$32 -> 550 | C20: =Assumptions!$B$31+C5*Assumptions!$B$32 -> 560 | D20: =Assumptions!$B$31+D5*Assumptions!$B$32 -> 572 | E20: =Assumptions!$B$31+E5*Assumptions!$B$32 -> 586.4 | F20: =Assumptions!$B$31+F5*Assumptions!$B$32 -> 603.7 | G20: =Assumptions!$B$31+G5*Assumptions!$B$32 -> 624.45 | H20: =Assumptions!$B$31+H5*Assumptions!$B$32 -> 643.1 | I20: =Assumptions!$B$31+I5*Assumptions!$B$32 -> 664.55 | ... AK20: =Assumptions!$B$31+AK5*Assumptions!$B$32 -> 4201.95
A21: Marketing (CAC) | B21: =B6*Assumptions!$B$33 -> 4000 | C21: =C6*Assumptions!$B$33 -> 800 | D21: =D6*Assumptions!$B$33 -> 960 | E21: =E6*Assumptions!$B$33 -> 1152 | F21: =F6*Assumptions!$B$33 -> 1384 | G21: =G6*Assumptions!$B$33 -> 1660 | H21: =H6*Assumptions!$B$33 -> 1492 | I21: =I6*Assumptions!$B$33 -> 1716 | ... AK21: =AK6*Assumptions!$B$33 -> 26924
A22: Other/compliance | B22: =Assumptions!$B$34+B17*Assumptions!$B$35 -> 2019.975 | C22: =Assumptions!$B$34+C17*Assumptions!$B$35 -> 2023.97 | D22: =Assumptions!$B$34+D17*Assumptions!$B$35 -> 2028.764 | E22: =Assumptions!$B$34+E17*Assumptions!$B$35 -> 2034.5168 | F22: =Assumptions!$B$34+F17*Assumptions!$B$35 -> 2041.4281 | G22: =Assumptions!$B$34+G17*Assumptions!$B$35 -> 2049.7178 | H22: =Assumptions!$B$34+H17*Assumptions!$B$35 -> 2057.1685 | I22: =Assumptions!$B$34+I17*Assumptions!$B$35 -> 2065.7377 | ... AK22: =Assumptions!$B$34+AK17*Assumptions!$B$35 -> 8910.6306
A23: Total opex | B23: =SUM(B19:B22) -> 51569.975 | C23: =SUM(C19:C22) -> 48383.97 | D23: =SUM(D19:D22) -> 48560.764 | E23: =SUM(E19:E22) -> 48772.917 | F23: =SUM(F19:F22) -> 49029.128 | G23: =SUM(G19:G22) -> 49334.168 | H23: =SUM(H19:H22) -> 79192.268 | I23: =SUM(I19:I22) -> 79446.288 | ... AK23: =SUM(AK19:AK22) -> 175036.58
A25: EBITDA (rev − rewards − opex) | B25: =B17-B11-B23 -> -58838.475 | C25: =C17-C11-C23 -> -57106.17 | D25: =D17-D11-D23 -> -59027.404 | E25: =E17-E11-E23 -> -61332.885 | F25: =F17-F11-F23 -> -64103.997 | G25: =G17-G11-G23 -> -67425.464 | H25: =H17-H11-H23 -> -99994.715 | I25: =I17-I11-I23 -> -103366.92 | ... AK25: =AK17-AK11-AK23 -> -93597.073
A26: Cumulative cash (incl. seed) | B26: =Assumptions!$B$37+B25 -> 1941161.5 | C26: =B26+C25 -> 1884055.4 | D26: =C26+D25 -> 1825028 | E26: =D26+E25 -> 1763695.1 | F26: =E26+F25 -> 1699591.1 | G26: =F26+G25 -> 1632165.6 | H26: =G26+H25 -> 1532170.9 | I26: =H26+I25 -> 1428804 | J26: =I26+J25 -> 1321551.8 | ... AK26: =AJ26+AK25 -> -2031496.4
A28: Reward coverage (rev ÷ rewards) | B28: =IF(B11=0,0,B17/B11) -> 0.052099635 | C28: =IF(C11=0,0,C17/C11) -> 0.052099635 | D28: =IF(D11=0,0,D17/D11) -> 0.052099635 | E28: =IF(E11=0,0,E17/E11) -> 0.052099635 | F28: =IF(F11=0,0,F17/F11) -> 0.052099635 | G28: =IF(G11=0,0,G17/G11) -> 0.052099635 | H28: =IF(H11=0,0,H17/H11) -> 0.052099635 | I28: =IF(I11=0,0,I17/I11) -> 0.052099635 | ... AK28: =IF(AK11=0,0,AK17/AK11) -> 2.4344734

Sheet Founder Outcome
A1: Founder Outcome — what has to be true
A3: Month-36 revenue run-rate (ARR, $) | B3: =Model!AK17*12 -> 1658551.3
A4: Month-36 riders | B4: =Model!AK5 -> 74039
A5: Month-36 rides/mo | B5: =Model!AK7 -> 740390
A6: Cash position at month 36 ($) | B6: =Model!AK26 -> -2031496.4
A7: Founder ownership | B7: =Assumptions!B39 -> 0.55
A9: Founder proceeds ($) = ARR × multiple × ownership
A10: Revenue multiple | B10: Base ARR (1x) | C10: Bull (2x ARR) | D10: Moon (4x ARR)
A11: 3 | B11: =$B$3*1*$A11*$B$7 -> 2736609.7 | C11: =$B$3*2*$A11*$B$7 -> 5473219.5 | D11: =$B$3*4*$A11*$B$7 -> 10946439
A12: 5 | B12: =$B$3*1*$A12*$B$7 -> 4561016.2 | C12: =$B$3*2*$A12*$B$7 -> 9122032.4 | D12: =$B$3*4*$A12*$B$7 -> 18244065
A13: 8 | B13: =$B$3*1*$A13*$B$7 -> 7297625.9 | C13: =$B$3*2*$A13*$B$7 -> 14595252 | D13: =$B$3*4*$A13*$B$7 -> 29190504
A14: 12 | B14: =$B$3*1*$A14*$B$7 -> 10946439 | C14: =$B$3*2*$A14*$B$7 -> 21892878 | D14: =$B$3*4*$A14*$B$7 -> 43785756
A16: Read: "rich" requires the Bull/Moon columns — i.e. premium conversion >5%, retention holding, and sponsor/wellness revenue compounding. The Assumptions tab is where those bets live. Not financial advice; ZEC volatility alone can move every $ figure 50% in a week (it just did).
